s3seek/__init__.py
s3seek-1.0.0.dist-info/LICENSE.txt
s3seek-1.0.0.dist-info/METADATA
s3seek-1.0.0.dist-info/WHEEL
s3seek-1.0.0.dist-info/top_level.txt
s3seek-1.0.0.dist-info/RECORD
