Metadata-Version: 2.1
Name: s3seek
Version: 1.0.0
Summary: File-like classes for interacting with AWS S3 buckets. In particular, for seek and partial download when reading.
Home-page: https://github.com/sanogenetics/s3seek
Author: Adam Faulconbridge
Author-email: afaulconbridge@googlemail.com
License: UNKNOWN
Platform: UNKNOWN
Provides-Extra: dev
Requires-Dist: pytest-cov ; extra == 'dev'
Requires-Dist: flake8 ; extra == 'dev'
Requires-Dist: black ; extra == 'dev'
Requires-Dist: pylint ; extra == 'dev'
Requires-Dist: pip-tools ; extra == 'dev'
Requires-Dist: pipdeptree ; extra == 'dev'
Requires-Dist: pre-commit ; extra == 'dev'
Requires-Dist: boto3 ; extra == 'dev'
